examples/__init__.py
examples/download_exovista.py
examples/exovista_sim.py
examples/simple_point_source.py
examples/star_exo.py
examples/visualize_throughput.py
pystarshade/__init__.py
pystarshade/propagator.py
pystarshade/simulate_field.py
pystarshade/apodization/__init__.py
pystarshade/apodization/apodize.py
pystarshade/apodization/pupil.py
pystarshade/data/__init__.py
pystarshade/data/drm.py
pystarshade/data/fields/__init__.py
pystarshade/data/masks/__init__.py
pystarshade/data/masks/grey_mask.py
pystarshade/data/masks/make_memmap.py
pystarshade/data/masks/mp_gen_mask.py
pystarshade/data/masks/starshade_edge_files/__init__.py
pystarshade/data/masks/starshade_masks/__init__.py
pystarshade/data/out/__init__.py
pystarshade/data/psf/__init__.py
pystarshade/data/pupils/__init__.py
pystarshade/data/scenes/__init__.py
pystarshade/diffraction/__init__.py
pystarshade/diffraction/bluestein_fft.py
pystarshade/diffraction/diffract.py
pystarshade/diffraction/field.py
pystarshade/diffraction/util.py
pystarshade-0.1.8.dist-info/LICENSE.txt
pystarshade-0.1.8.dist-info/METADATA
pystarshade-0.1.8.dist-info/WHEEL
pystarshade-0.1.8.dist-info/top_level.txt
pystarshade-0.1.8.dist-info/RECORD
