Metadata-Version: 2.1
Name: pystarshade
Version: 0.1.8
Summary: A python package for starshade imaging simulations
Home-page: https://github.com/xiaziyna/PyStarshade
Author: Jamila Taaki
Author-email: xiaziyna@gmail.com
Classifier: Development Status :: 2 - Pre-Alpha
Classifier: Intended Audience :: Science/Research
Classifier: License :: OSI Approved :: GNU General Public License v3 (GPLv3)
Classifier: Operating System :: OS Independent
Classifier: Programming Language :: Python :: 3
Classifier: Programming Language :: Python :: 3.6
Classifier: Programming Language :: Python :: 3.7
Classifier: Programming Language :: Python :: 3.8
Classifier: Programming Language :: Python :: 3.9
Requires-Python: >=3.6
License-File: LICENSE.txt
Requires-Dist: numpy
Requires-Dist: scipy
Provides-Extra: extra
Requires-Dist: hcipy; extra == "extra"
Requires-Dist: astropy; extra == "extra"
